nest/__init__.py
nest/command_line.py
nest/helpers.py
nest/nest.py
python_google_nest-5.2.1.dist-info/LICENSE.md
python_google_nest-5.2.1.dist-info/METADATA
python_google_nest-5.2.1.dist-info/WHEEL
python_google_nest-5.2.1.dist-info/entry_points.txt
python_google_nest-5.2.1.dist-info/top_level.txt
python_google_nest-5.2.1.dist-info/RECORD
