Metadata-Version: 2.1
Name: python-google-nest
Version: 5.2.1
Summary: Python API and command line tool for talking to the Nest™ Thermostat through new Google API
Home-page: https://github.com/axlan/python-nest/
Author: Jonathan Diamond
Author-email: feros32@gmail.com
Keywords: nest thermostat
Classifier: Programming Language :: Python :: 3
Classifier: Operating System :: OS Independent
Requires-Python: >=3.6
License-File: LICENSE.md
Requires-Dist: requests-oauthlib
